thinkhive/__init__.py
thinkhive/client.py
thinkhive/api/__init__.py
thinkhive/api/analyzer.py
thinkhive/api/business_metrics.py
thinkhive/api/calibration.py
thinkhive/api/claims.py
thinkhive/api/conversation_eval.py
thinkhive/api/deterministic_graders.py
thinkhive/api/eval_health.py
thinkhive/api/human_review.py
thinkhive/api/issues.py
thinkhive/api/nondeterminism.py
thinkhive/api/roi_analytics.py
thinkhive/api/runs.py
thinkhive/api/traces.py
thinkhive/api/transcript_patterns.py
thinkhive-3.2.0.dist-info/METADATA
thinkhive-3.2.0.dist-info/WHEEL
thinkhive-3.2.0.dist-info/top_level.txt
thinkhive-3.2.0.dist-info/RECORD
